django_migrations_ci/__init__.py
django_migrations_ci/backends/__init__.py
django_migrations_ci/backends/mysql.py
django_migrations_ci/backends/postgresql.py
django_migrations_ci/backends/sqlite.py
django_migrations_ci/conf.py
django_migrations_ci/django.py
django_migrations_ci/management/__init__.py
django_migrations_ci/management/commands/__init__.py
django_migrations_ci/management/commands/migrateci.py
django_migrations_ci/pytest_plugin.py
django_migrations_ci/shell.py
django_migrations_ci-0.12.dist-info/LICENSE
django_migrations_ci-0.12.dist-info/METADATA
django_migrations_ci-0.12.dist-info/WHEEL
django_migrations_ci-0.12.dist-info/entry_points.txt
django_migrations_ci-0.12.dist-info/RECORD
